<TITLE>Происходит краш приложения в настройке Notification в поле секции Crypto при удалении первой по счету криптовалюты из двух оставшихся с иконками "минус"</TITLE>
<PRECONDITION>Запустить приложение</PRECONDITION>
<STR> 1. В нижней панели навигации выбрать закладку Notification
      2. Зайти в настройки Notification
      3. Выбрать из списка в поле секции Crypto три криптовалюты/сохранить изменения
      4. Нажать кнопку Edit  в поле секции Crypto
      5. Удалить первую по списку криптовалюту в открывщемся списке криптовалют/сохранить изменения
      6. Удалить первую по списку криптовалюту из двух оставшихся нажав на иконку "минус" справа от названия валюты" </STR>
 <AR>Происходит краш приложения в настройке Notification в поле секции Crypto при удалении первой по счету криптовалюты из двух оставшихся с иконками "минус"</AR>
 <ER>При настройке Notification в поле секции Crypto все криптовалюты из списка удаляются нажатием на иконку "минус"<ER>
